ansys/api/geometry/VERSION
ansys/api/geometry/__init__.py
ansys/api/geometry/py.typed
ansys/api/geometry/v0/__init__.py
ansys/api/geometry/v0/bodies.proto
ansys/api/geometry/v0/bodies_pb2.py
ansys/api/geometry/v0/bodies_pb2.pyi
ansys/api/geometry/v0/bodies_pb2_grpc.py
ansys/api/geometry/v0/bodies_pb2_grpc.pyi
ansys/api/geometry/v0/commands.proto
ansys/api/geometry/v0/commands_pb2.py
ansys/api/geometry/v0/commands_pb2.pyi
ansys/api/geometry/v0/commands_pb2_grpc.py
ansys/api/geometry/v0/commands_pb2_grpc.pyi
ansys/api/geometry/v0/components.proto
ansys/api/geometry/v0/components_pb2.py
ansys/api/geometry/v0/components_pb2.pyi
ansys/api/geometry/v0/components_pb2_grpc.py
ansys/api/geometry/v0/components_pb2_grpc.pyi
ansys/api/geometry/v0/coordinatesystems.proto
ansys/api/geometry/v0/coordinatesystems_pb2.py
ansys/api/geometry/v0/coordinatesystems_pb2.pyi
ansys/api/geometry/v0/coordinatesystems_pb2_grpc.py
ansys/api/geometry/v0/coordinatesystems_pb2_grpc.pyi
ansys/api/geometry/v0/curves.proto
ansys/api/geometry/v0/curves_pb2.py
ansys/api/geometry/v0/curves_pb2.pyi
ansys/api/geometry/v0/curves_pb2_grpc.py
ansys/api/geometry/v0/curves_pb2_grpc.pyi
ansys/api/geometry/v0/datumplanes.proto
ansys/api/geometry/v0/datumplanes_pb2.py
ansys/api/geometry/v0/datumplanes_pb2.pyi
ansys/api/geometry/v0/datumplanes_pb2_grpc.py
ansys/api/geometry/v0/datumplanes_pb2_grpc.pyi
ansys/api/geometry/v0/edges.proto
ansys/api/geometry/v0/edges_pb2.py
ansys/api/geometry/v0/edges_pb2.pyi
ansys/api/geometry/v0/edges_pb2_grpc.py
ansys/api/geometry/v0/edges_pb2_grpc.pyi
ansys/api/geometry/v0/faces.proto
ansys/api/geometry/v0/faces_pb2.py
ansys/api/geometry/v0/faces_pb2.pyi
ansys/api/geometry/v0/faces_pb2_grpc.py
ansys/api/geometry/v0/faces_pb2_grpc.pyi
ansys/api/geometry/v0/facettools.proto
ansys/api/geometry/v0/facettools_pb2.py
ansys/api/geometry/v0/facettools_pb2.pyi
ansys/api/geometry/v0/facettools_pb2_grpc.py
ansys/api/geometry/v0/facettools_pb2_grpc.pyi
ansys/api/geometry/v0/materials.proto
ansys_api_geometry-0.4.91.dist-info/licenses/LICENSE
ansys_api_geometry-0.4.91.dist-info/METADATA
ansys_api_geometry-0.4.91.dist-info/WHEEL
ansys_api_geometry-0.4.91.dist-info/entry_points.txt
ansys_api_geometry-0.4.91.dist-info/top_level.txt
ansys_api_geometry-0.4.91.dist-info/RECORD
