Metadata-Version: 2.4
Name: ansys-api-geometry
Version: 0.4.91
Summary: Autogenerated Python gRPC interface package for ansys-api-geometry, built on 06:45:41 on 21 January 2026
Home-page: https://github.com/ansys/ansys-api-geometry
Author: ANSYS, Inc.
Author-email: pyansys.core@ansys.com
Maintainer: ANSYS, Inc.
Maintainer-email: pyansys.core@ansys.com
License: MIT
Project-URL: Documentation, https://github.com/ansys/ansys-api-geometry/#readme
Project-URL: Source, https://github.com/ansys/ansys-api-geometry/
Project-URL: Tracker, https://github.com/ansys/ansys-api-geometry/issues/
Requires-Python: >=3.10
License-File: LICENSE
Requires-Dist: grpcio~=1.44
Requires-Dist: protobuf<7,>=3.19
Requires-Dist: ansys-api-dbu==0.3.28
Dynamic: author
Dynamic: author-email
Dynamic: description
Dynamic: description-content-type
Dynamic: home-page
Dynamic: license
Dynamic: license-file
Dynamic: maintainer
Dynamic: maintainer-email
Dynamic: project-url
Dynamic: requires-dist
Dynamic: requires-python
Dynamic: summary
